Metadata-Version: 2.4
Name: llama-index-vector-stores-clickhouse
Version: 0.6.1
Summary: llama-index vector_stores clickhouse integration
Author-email: ClickHouse <info@clickhouse.com>
License-Expression: MIT
License-File: LICENSE
Requires-Python: <4.0,>=3.9
Requires-Dist: clickhouse-connect>=0.7.0
Requires-Dist: llama-index-core<0.15,>=0.13.0
